dir2aisnap/__init__.py
dir2aisnap/dir2aisnap.py
dir2aisnap-0.1.0.dist-info/METADATA
dir2aisnap-0.1.0.dist-info/WHEEL
dir2aisnap-0.1.0.dist-info/entry_points.txt
dir2aisnap-0.1.0.dist-info/licenses/LICENSE
dir2aisnap-0.1.0.dist-info/RECORD
