Metadata-Version: 2.4
Name: dir2aisnap
Version: 0.1.0
Summary: Convert directory structure into a single text file while respecting .gitignore rules
Author-email: Yoshikazu Kawataki <kawataki-yoshika@dmm.com>
License-File: LICENSE
Classifier: Development Status :: 3 - Alpha
Classifier: Environment :: Console
Classifier: License :: OSI Approved :: MIT License
Classifier: Operating System :: OS Independent
Classifier: Programming Language :: Python :: 3
Classifier: Topic :: Software Development :: Libraries :: Python Modules
Classifier: Topic :: Utilities
Requires-Python: >=3.7
